Pyquery141ZhongwenWendang/README.md
Pyquery141ZhongwenWendang/__init__.py
Pyquery141ZhongwenWendang/__main__.py
Pyquery141ZhongwenWendang/file.epub
Pyquery141ZhongwenWendang/index.html
Pyquery141ZhongwenWendang/css/__init__.py
Pyquery141ZhongwenWendang/css/annotations.css
Pyquery141ZhongwenWendang/css/main.css
Pyquery141ZhongwenWendang/css/normalize.css
Pyquery141ZhongwenWendang/css/popup.css
Pyquery141ZhongwenWendang/font/__init__.py
Pyquery141ZhongwenWendang/font/fontello.eot
Pyquery141ZhongwenWendang/font/fontello.svg
Pyquery141ZhongwenWendang/font/fontello.ttf
Pyquery141ZhongwenWendang/font/fontello.woff
Pyquery141ZhongwenWendang/img/__init__.py
Pyquery141ZhongwenWendang/img/annotator-glyph-sprite.png
Pyquery141ZhongwenWendang/img/annotator-icon-sprite.png
Pyquery141ZhongwenWendang/img/apple-touch-icon.png
Pyquery141ZhongwenWendang/img/cancelfullscreen.png
Pyquery141ZhongwenWendang/img/close.png
Pyquery141ZhongwenWendang/img/fullscreen.png
Pyquery141ZhongwenWendang/img/loader.gif
Pyquery141ZhongwenWendang/img/menu-icon.png
Pyquery141ZhongwenWendang/img/save.png
Pyquery141ZhongwenWendang/img/saved.png
Pyquery141ZhongwenWendang/img/settings-s.png
Pyquery141ZhongwenWendang/img/settings.png
Pyquery141ZhongwenWendang/img/star.png
Pyquery141ZhongwenWendang/js/__init__.py
Pyquery141ZhongwenWendang/js/epub.js
Pyquery141ZhongwenWendang/js/epub.min.js
Pyquery141ZhongwenWendang/js/epub.min.map
Pyquery141ZhongwenWendang/js/hooks.min.js
Pyquery141ZhongwenWendang/js/hooks.min.map
Pyquery141ZhongwenWendang/js/reader.js
Pyquery141ZhongwenWendang/js/reader.js.map
Pyquery141ZhongwenWendang/js/reader.min.js
Pyquery141ZhongwenWendang/js/reader.min.map
Pyquery141ZhongwenWendang/js/hooks/__init__.py
Pyquery141ZhongwenWendang/js/hooks/extensions/__init__.py
Pyquery141ZhongwenWendang/js/hooks/extensions/highlight.js
Pyquery141ZhongwenWendang/js/libs/__init__.py
Pyquery141ZhongwenWendang/js/libs/jquery.min.js
Pyquery141ZhongwenWendang/js/libs/localforage.min.js
pyquery_1_4_1_zhongwen_wendang-2024.3.4.0.dist-info/METADATA
pyquery_1_4_1_zhongwen_wendang-2024.3.4.0.dist-info/WHEEL
pyquery_1_4_1_zhongwen_wendang-2024.3.4.0.dist-info/entry_points.txt
pyquery_1_4_1_zhongwen_wendang-2024.3.4.0.dist-info/top_level.txt
pyquery_1_4_1_zhongwen_wendang-2024.3.4.0.dist-info/RECORD
